languru/VERSION
languru/__init__.py
languru/examples/__init__.py
languru/examples/tools.py
languru/openai_agents/__init__.py
languru/openai_agents/messages.py
languru/openai_agents/stream_handler.py
languru/openai_chatcmpl/__init__.py
languru/openai_chatcmpl/handler.py
languru/openai_chatcmpl/stream_handler.py
languru/openai_responses/__init__.py
languru/openai_responses/stream_handler.py
languru/openai_shared/__init__.py
languru/openai_shared/audio.py
languru/openai_shared/messages.py
languru/openai_shared/tools.py
languru-0.23.3.dist-info/LICENSE
languru-0.23.3.dist-info/METADATA
languru-0.23.3.dist-info/WHEEL
languru-0.23.3.dist-info/RECORD
